onnxocr/__init__.py
onnxocr/cls_postprocess.py
onnxocr/db_postprocess.py
onnxocr/imaug.py
onnxocr/logger.py
onnxocr/ocr_images_pdfs.py
onnxocr/onnx_paddleocr.py
onnxocr/operators.py
onnxocr/predict_base.py
onnxocr/predict_cls.py
onnxocr/predict_det.py
onnxocr/predict_rec.py
onnxocr/predict_system.py
onnxocr/rec_postprocess.py
onnxocr/utils.py
onnxocr/models/ch_ppocr_server_v2.0/ppocr_keys_v1.txt
onnxocr/models/ch_ppocr_server_v2.0/cls/cls.onnx
onnxocr/models/ch_ppocr_server_v2.0/det/det.onnx
onnxocr/models/ppocrv4/cls/cls.onnx
onnxocr/models/ppocrv4/det/det.onnx
onnxocr/models/ppocrv4/rec/rec.onnx
onnxocr/models/ppocrv5/ppocrv5_dict.txt
onnxocr/models/ppocrv5/cls/cls.onnx
onnxocr/models/ppocrv5/det/det.onnx
onnxocr/models/ppocrv5/rec/rec.onnx
onnxocr-2025.5.dist-info/licenses/LICENSE
onnxocr-2025.5.dist-info/METADATA
onnxocr-2025.5.dist-info/WHEEL
onnxocr-2025.5.dist-info/top_level.txt
onnxocr-2025.5.dist-info/RECORD
