Metadata-Version: 2.4
Name: onnxocr
Version: 2025.5
Summary: A lightweight OCR system based on PaddleOCR
Home-page: https://github.com/jingsongliujing/OnnxOCR
Author: jingsongliujing
Author-email: jingsongliujing <45508593+jingsongliujing@users.noreply.github.com>
License-Expression: Apache-2.0
Project-URL: Homepage, https://github.com/jingsongliujing/OnnxOCR
Project-URL: Repository, https://github.com/jingsongliujing/OnnxOCR
Project-URL: Issues, https://github.com/jingsongliujing/issues
Classifier: Programming Language :: Python :: 3
Classifier: Development Status :: 4 - Beta
Requires-Python: >=3.6
License-File: LICENSE
Requires-Dist: opencv-python-headless
Requires-Dist: opencv-contrib-python
Requires-Dist: onnxruntime
Requires-Dist: shapely
Requires-Dist: pyclipper
Requires-Dist: numpy<2.0.0
Requires-Dist: pymupdf
Requires-Dist: pdf2image
Dynamic: author
Dynamic: home-page
Dynamic: license-file
Dynamic: requires-python
